examples/__init__.py
examples/example_eval_atari.py
examples/example_eval_memory_loading.py
examples/example_eval_memory_saving.py
examples/example_eval_replay.py
examples/example_eval_rollout.py
examples/example_train_atari.py
examples/example_train_replay copy.py
examples/example_train_replay.py
examples/example_train_rollout.py
examples/example_watch_atari.py
examples/example_watch_replay.py
examples/example_watch_rollout.py
sb3_extra_buffers/__init__.py
sb3_extra_buffers/current_version.py
sb3_extra_buffers/py.typed
sb3_extra_buffers/version.txt
sb3_extra_buffers/compressed/__init__.py
sb3_extra_buffers/compressed/base.py
sb3_extra_buffers/compressed/compressed_array.py
sb3_extra_buffers/compressed/compressed_replay.py
sb3_extra_buffers/compressed/compressed_rollout.py
sb3_extra_buffers/compressed/utils.py
sb3_extra_buffers/compressed/compression_methods/__init__.py
sb3_extra_buffers/compressed/compression_methods/compression_methods.py
sb3_extra_buffers/compressed/compression_methods/compression_methods_lz4.py
sb3_extra_buffers/compressed/compression_methods/compression_methods_numba.py
sb3_extra_buffers/compressed/compression_methods/compression_methods_zstd.py
sb3_extra_buffers/gpu_buffers/__init__.py
sb3_extra_buffers/gpu_buffers/raw_buffer.py
sb3_extra_buffers/gpu_buffers/utils.py
sb3_extra_buffers/gpu_buffers/compression_methods/__init__.py
sb3_extra_buffers/gpu_buffers/compression_methods/compression_methods.py
sb3_extra_buffers/recording/__init__.py
sb3_extra_buffers/recording/base.py
sb3_extra_buffers/recording/dummy_record_buffers.py
sb3_extra_buffers/recording/record_buffer.py
sb3_extra_buffers/recording/utils.py
sb3_extra_buffers/training_utils/__init__.py
sb3_extra_buffers/training_utils/atari.py
sb3_extra_buffers/training_utils/buffer_warmup.py
sb3_extra_buffers/training_utils/eval_model.py
sb3_extra_buffers/vec_buf/__init__.py
sb3_extra_buffers/vec_buf/buffers.py
sb3_extra_buffers-0.4.3.dist-info/licenses/LICENSE
sb3_extra_buffers-0.4.3.dist-info/METADATA
sb3_extra_buffers-0.4.3.dist-info/WHEEL
sb3_extra_buffers-0.4.3.dist-info/top_level.txt
sb3_extra_buffers-0.4.3.dist-info/RECORD
