Metadata-Version: 2.4
Name: sb3_extra_buffers
Version: 0.4.3
Summary: Extra buffer classes for Stable-Baselines3, reduce memory usage with minimal overhead.
Home-page: https://github.com/Trenza1ore/sb3-extra-buffers
Author: Hugo (Jin Huang)
Author-email: SushiNinja123@outlook.com
License: MIT
Project-URL: Source Code, https://github.com/Trenza1ore/sb3-extra-buffers
Project-URL: Stable-Baselines3, https://github.com/DLR-RM/stable-baselines3
Project-URL: Stable-Baselines3 - Contrib, https://github.com/Stable-Baselines-Team/stable-baselines3-contrib
Requires-Python: >=3.9
License-File: LICENSE
Requires-Dist: stable_baselines3
Requires-Dist: tqdm
Provides-Extra: isal
Requires-Dist: isal; extra == "isal"
Provides-Extra: numba
Requires-Dist: numba; extra == "numba"
Provides-Extra: zstd
Requires-Dist: zstd; extra == "zstd"
Provides-Extra: lz4
Requires-Dist: lz4; extra == "lz4"
Provides-Extra: fast
Requires-Dist: sb3_extra_buffers[isal,lz4,numba,zstd]; extra == "fast"
Provides-Extra: extra
Requires-Dist: stable_baselines3[extra]; extra == "extra"
Provides-Extra: atari
Requires-Dist: sb3_extra_buffers[extra]; extra == "atari"
Provides-Extra: vizdoom
Requires-Dist: sb3_extra_buffers[extra]; extra == "vizdoom"
Requires-Dist: vizdoom; extra == "vizdoom"
Dynamic: author
Dynamic: author-email
Dynamic: description
Dynamic: description-content-type
Dynamic: home-page
Dynamic: license
Dynamic: license-file
Dynamic: project-url
Dynamic: provides-extra
Dynamic: requires-dist
Dynamic: requires-python
Dynamic: summary
